cssm.cpython-310-darwin.so
ssms/__init__.py
ssms/dataset_generators/__init__.py
ssms/dataset_generators/snpe.py
ssms/dataset_generators/lan_mlp.py
ssms/config/config.py
ssms/config/__init__.py
ssms/basic_simulators/__init__.py
ssms/basic_simulators/drift_functions.py
ssms/basic_simulators/simulator.py
ssms/basic_simulators/boundary_functions.py
ssms/support_utils/__init__.py
ssms/support_utils/kde_class.py
ssm_simulators-2.dist-info/RECORD
ssm_simulators-2.dist-info/LICENSE
ssm_simulators-2.dist-info/WHEEL
ssm_simulators-2.dist-info/top_level.txt
ssm_simulators-2.dist-info/METADATA
