Metadata-Version: 2.1
Name: ssm-simulators
Version: 2
Summary: SSMS is a package collecting simulators and training data generators for a bunch of generative models of interest in the cognitive science / neuroscience and approximate bayesian computation communities
Author-email: Alexander Fenger <alexander_fengler@brown.edu>
Project-URL: Homepage, https://github.com/AlexanderFengler/ssm-simulators
Project-URL: Bug Tracker, https://github.com/AlexanderFengler/ssm-simulators/issues
Keywords: simulators,generative models,cognitive science,neuroscience
Classifier: Development Status :: 1 - Planning
Classifier: Environment :: Console
Classifier: License :: OSI Approved :: MIT License
Classifier: Programming Language :: Python
Classifier: Topic :: Scientific/Engineering
Requires-Python: <3.12,>3.8
License-File: LICENSE
Requires-Dist: numpy >=1.17.0
Requires-Dist: scipy >=1.6.3
Requires-Dist: cython >=0.29.23
Requires-Dist: pandas >=1.0.0
Requires-Dist: scikit-learn >=0.24.0
Requires-Dist: psutil >=5.0.0
Provides-Extra: dev
Requires-Dist: black ; extra == 'dev'
Requires-Dist: ruff ; extra == 'dev'
Requires-Dist: pytest ; extra == 'dev'
